simpleio/__init__.py
simpleio/simpleio.py
simpleio-0.1.3.dist-info/METADATA
simpleio-0.1.3.dist-info/WHEEL
simpleio-0.1.3.dist-info/top_level.txt
simpleio-0.1.3.dist-info/RECORD
