Metadata-Version: 2.1
Name: simpleio
Version: 0.1.3
Summary: simple loading/dumping of common data formats
Home-page: UNKNOWN
Author: Norman Müller
Author-email: norman.mueller@tum.de
License: UNKNOWN
Platform: UNKNOWN
Classifier: Programming Language :: Python :: 3
Classifier: License :: OSI Approved :: MIT License
Classifier: Operating System :: OS Independent
Requires-Python: >=3.6
Requires-Dist: orjson
Requires-Dist: numpy
